mofid_singular_finder/__init__.py
mofid_singular_finder/data_helper.py
mofid_singular_finder/detector.py
mofid_singular_finder/version.py
mofid_singular_finder/resource/affix.json
mofid_singular_finder/resource/exceptions.txt
mofid_singular_finder/resource/stemmer/mokasar.txt
mofid_singular_finder/resource/stemmer/original_parsivar_stem_lex.pckl
mofid_singular_finder/resource/stemmer/stem_irregularNounDict.pckl
mofid_singular_finder/resource/stemmer/stem_lex.pckl
mofid_singular_finder/resource/stemmer/stem_verbMap.pckl
mofid_singular_finder/resource/stemmer/verbStemDict.pckl
mofid_singular_finder/resource/stemmer/verb_tenses.json
mofid_singular_finder-0.0.5.dist-info/METADATA
mofid_singular_finder-0.0.5.dist-info/WHEEL
mofid_singular_finder-0.0.5.dist-info/top_level.txt
mofid_singular_finder-0.0.5.dist-info/RECORD
