Metadata-Version: 2.1
Name: mofid-singular-finder
Version: 0.0.5
Summary: A simple library for finding words with Second person singular pronouns.
Home-page: UNKNOWN
Author: ali96ebrahimi@gmail.com
License: MIT
Platform: UNKNOWN
